setup.py
GeoFuns/__init__.py
GeoFuns/geo_queries.py
GeoFuns/geofunctions.py
GeoFuns/places.py
harryritchie.egg-info/PKG-INFO
harryritchie.egg-info/SOURCES.txt
harryritchie.egg-info/dependency_links.txt
harryritchie.egg-info/requires.txt
harryritchie.egg-info/top_level.txt