Metadata-Version: 1.2
Name: harryritchie
Version: 0.3.0
Summary: A package for geo tools used to map card score
Home-page: https://github.com/pypa/sampleproject
Author: Harry Ritchie
Author-email: harry.ritchie@prea.eu
License: UNKNOWN
Platform: UNKNOWN
Classifier: Programming Language :: Python :: 3
Classifier: License :: OSI Approved :: MIT License
Classifier: Operating System :: OS Independent
Requires-Python: >=3.6
